{
  "__url__": "https://www.nexon.com/maplestory/news/update/4352/updated-april-11-v-203-arcade-adventures-patch-notes",
  "__date__": "Mar 5, 2019",
  "__title__": "Arcade Adventures",
  "Retro World Events": [
    "Promote the Game!",
    "Chief's Special Potion",
    "Mercenary's Jump Training",
    "Magician's Dodge Training",
    "Demon King's Tower",
    "Eliminate Bug Monsters!",
    "Retro Reach",
    "Call of the Goddess",
    "Retro World Coin Shop"
  ],
  "Additional Updates": [
    "Bug Fixes",
    "Other Changes"
  ],
  "Detective Rave's Case Notes": [
    "Theme Dungeon",
    "Detective Rave Open Celebration Event"
  ],
  "Other New Events": [
    "Peplock Holmes Detective Office",
    "Spot the Difference",
    "Sunny Sunday Perk",
    "Hot Week",
    "Spell Trace Fever Time"
  ]
}