{
  "__url__": "https://www.nexon.com/maplestory/news/update/4393/updated-march-19-v212-maple-story-x-isekai-quartet-patch-notes",
  "__date__": "Mar 9, 2020",
  "__title__": "MapleStory X ISEKAI QUARTET",
  "New Updates": [
    "Maple Tour",
    "Mu Lung Dojo Expansion",
    "Ghost Park Ranked Mode",
    "Job Balances",
    "Content Changes",
    "System Changes",
    "Bug Fixes",
    "Known Issues"
  ],
  "MapleStory X ISEKAI QUARTET Events": [
    "Daily Requests",
    "Field Trips",
    "Isekai Match"
  ]
}